<?xml version="1.0" encoding="utf-8"?><sf:SMARTSTYLE xmlns:sf="urn:sap-com:SmartForms:2000:style-internal-structure" xmlns="urn:sap-com:sdixml-ifr:2000" sf:language="EN"><sf:HEADER><STYLENAME>Z6MM001S_STYLE_SF</STYLENAME><MASTERLANG>E</MASTERLANG><VERSION>00210</VERSION><FIRSTUSER>RAJESH</FIRSTUSER><FIRSTDATE>2007-06-21</FIRSTDATE><FIRSTTIME>09:59:51</FIRSTTIME><LASTUSER>IBMABAP01</LASTUSER><LASTDATE>2010-09-30</LASTDATE><LASTTIME>15:54:03</LASTTIME><LANGU>E</LANGU><CAPTION>Style for  PSF</CAPTION><V_CAPTION>Style YPCC_SF</V_CAPTION><TDFIRSTPAR>ST</TDFIRSTPAR><CPI>10.00</CPI><LPI>6.00</LPI><TDTABDIST>1.00</TDTABDIST><TDTABDISTU>CM</TDTABDISTU><ACTIVE>A</ACTIVE><TDFAMILY>TIMES</TDFAMILY><TDHEIGHT>100</TDHEIGHT><TDULPOS>0.00</TDULPOS><TDULTHICK>0.00</TDULTHICK><TDULGREY>000</TDULGREY><RED>000</RED><GREEN>000</GREEN><BLUE>000</BLUE><TRANS>000</TRANS></sf:HEADER><sf:PARAGRAPHS><item><ACTIVE>A</ACTIVE><STYLENAME>Z6MM001S_STYLE_SF</STYLENAME><TDPARGRAPH>C1</TDPARGRAPH><TDPJUSTIFY>CENTER</TDPJUSTIFY><TDPLDIST>1.00</TDPLDIST><TDPLDISTU>LN</TDPLDISTU><TDPTOP>0.00</TDPTOP><TDPTOPU>CM</TDPTOPU><TDPBOT>0.00</TDPBOT><TDPBOTU>CM</TDPBOTU><TDPLEFT>0.00</TDPLEFT><TDPLEFTU>CM</TDPLEFTU><TDPRIGHT>0.00</TDPRIGHT><TDPRIGHTU>CM</TDPRIGHTU><TDPENTRY>0.00</TDPENTRY><TDPENTRYU>CM</TDPENTRYU><TDNUMLEFT>0.00</TDNUMLEFT><TDNUMOUTL>00</TDNUMOUTL><TDLDEPTH>00</TDLDEPTH><TDLFIRSTIN>0</TDLFIRSTIN><TDLNEXTIND>0</TDLNEXTIND><TDLCOUNT>0</TDLCOUNT><TDFAMILY>TIMES</TDFAMILY><TDHEIGHT>100</TDHEIGHT><TDBOLD>*</TDBOLD><TDITALIC>*</TDITALIC><TDUNDERLIN>*</TDUNDERLIN><TDULPOS>0.00</TDULPOS><TDULTHICK>0.00</TDULTHICK><TDULGREY>000</TDULGREY><RED>000</RED><GREEN>000</GREEN><BLUE>000</BLUE><TRANS>000</TRANS><LANGU>E</LANGU><CAPTION>C  TIMES 10</CAPTION></item><item><ACTIVE>A</ACTIVE><STYLENAME>Z6MM001S_STYLE_SF</STYLENAME><TDPARGRAPH>C2</TDPARGRAPH><TDPJUSTIFY>CENTER</TDPJUSTIFY><TDPLDIST>0.70</TDPLDIST><TDPLDISTU>LN</TDPLDISTU><TDPTOP>0.00</TDPTOP><TDPTOPU>CM</TDPTOPU><TDPBOT>0.00</TDPBOT><TDPBOTU>CM</TDPBOTU><TDPLEFT>0.00</TDPLEFT><TDPLEFTU>CM</TDPLEFTU><TDPRIGHT>0.00</TDPRIGHT><TDPRIGHTU>CM</TDPRIGHTU><TDPENTRY>0.00</TDPENTRY><TDPENTRYU>CM</TDPENTRYU><TDNUMLEFT>0.00</TDNUMLEFT><TDNUMOUTL>00</TDNUMOUTL><TDLDEPTH>00</TDLDEPTH><TDLFIRSTIN>0</TDLFIRSTIN><TDLNEXTIND>0</TDLNEXTIND><TDLCOUNT>0</TDLCOUNT><TDFAMILY>TIMES</TDFAMILY><TDHEIGHT>080</TDHEIGHT><TDBOLD>X</TDBOLD><TDITALIC>*</TDITALIC><TDUNDERLIN>*</TDUNDERLIN><TDULPOS>0.00</TDULPOS><TDULTHICK>0.00</TDULTHICK><TDULGREY>000</TDULGREY><RED>000</RED><GREEN>000</GREEN><BLUE>000</BLUE><TRANS>000</TRANS><LANGU>E</LANGU><CAPTION>C TIMES 8 Bold</CAPTION></item><item><ACTIVE>A</ACTIVE><STYLENAME>Z6MM001S_STYLE_SF</STYLENAME><TDPARGRAPH>C3</TDPARGRAPH><TDPJUSTIFY>CENTER</TDPJUSTIFY><TDPLDIST>1.00</TDPLDIST><TDPLDISTU>LN</TDPLDISTU><TDPTOP>0.00</TDPTOP><TDPTOPU>CM</TDPTOPU><TDPBOT>0.00</TDPBOT><TDPBOTU>CM</TDPBOTU><TDPLEFT>0.00</TDPLEFT><TDPLEFTU>CM</TDPLEFTU><TDPRIGHT>0.00</TDPRIGHT><TDPRIGHTU>CM</TDPRIGHTU><TDPENTRY>0.00</TDPENTRY><TDPENTRYU>CM</TDPENTRYU><TDNUMLEFT>0.00</TDNUMLEFT><TDNUMLEFTU>CM</TDNUMLEFTU><TDNUMOUTL>00</TDNUMOUTL><TDLDEPTH>00</TDLDEPTH><TDLFIRSTIN>0</TDLFIRSTIN><TDLNEXTIND>0</TDLNEXTIND><TDLCOUNT>0</TDLCOUNT><TDFAMILY>TIMES</TDFAMILY><TDHEIGHT>140</TDHEIGHT><TDBOLD>X</TDBOLD><TDITALIC>*</TDITALIC><TDUNDERLIN>*</TDUNDERLIN><TDULPOS>0.00</TDULPOS><TDULTHICK>0.00</TDULTHICK><TDULGREY>000</TDULGREY><RED>000</RED><GREEN>000</GREEN><BLUE>000</BLUE><TRANS>000</TRANS><LANGU>E</LANGU><CAPTION>C  TIMES 14</CAPTION></item><item><ACTIVE>A</ACTIVE><STYLENAME>Z6MM001S_STYLE_SF</STYLENAME><TDPARGRAPH>C4</TDPARGRAPH><TDPJUSTIFY>CENTER</TDPJUSTIFY><TDPLDIST>1.00</TDPLDIST><TDPLDISTU>LN</TDPLDISTU><TDPTOP>0.00</TDPTOP><TDPTOPU>CM</TDPTOPU><TDPBOT>0.00</TDPBOT><TDPBOTU>CM</TDPBOTU><TDPLEFT>0.00</TDPLEFT><TDPLEFTU>CM</TDPLEFTU><TDPRIGHT>0.00</TDPRIGHT><TDPRIGHTU>CM</TDPRIGHTU><TDPENTRY>0.00</TDPENTRY><TDPENTRYU>CM</TDPENTRYU><TDNUMLEFT>0.00</TDNUMLEFT><TDNUMLEFTU>CM</TDNUMLEFTU><TDNUMOUTL>00</TDNUMOUTL><TDLDEPTH>00</TDLDEPTH><TDLFIRSTIN>0</TDLFIRSTIN><TDLNEXTIND>0</TDLNEXTIND><TDLCOUNT>0</TDLCOUNT><TDFAMILY>TIMES</TDFAMILY><TDHEIGHT>080</TDHEIGHT><TDBOLD>*</TDBOLD><TDITALIC>*</TDITALIC><TDUNDERLIN>*</TDUNDERLIN><TDULPOS>0.00</TDULPOS><TDULTHICK>0.00</TDULTHICK><TDULGREY>000</TDULGREY><RED>000</RED><GREEN>000</GREEN><BLUE>000</BLUE><TRANS>000</TRANS><LANGU>E</LANGU><CAPTION>C TIMES 8</CAPTION></item><item><ACTIVE>A</ACTIVE><STYLENAME>Z6MM001S_STYLE_SF</STYLENAME><TDPARGRAPH>C5</TDPARGRAPH><TDPJUSTIFY>BLOCK</TDPJUSTIFY><TDPLDIST>0.50</TDPLDIST><TDPLDISTU>LN</TDPLDISTU><TDPTOP>0.00</TDPTOP><TDPTOPU>CM</TDPTOPU><TDPBOT>0.00</TDPBOT><TDPBOTU>CM</TDPBOTU><TDPLEFT>0.00</TDPLEFT><TDPLEFTU>CM</TDPLEFTU><TDPRIGHT>0.00</TDPRIGHT><TDPRIGHTU>CM</TDPRIGHTU><TDPENTRY>0.00</TDPENTRY><TDPENTRYU>CM</TDPENTRYU><TDNUMLEFT>0.00</TDNUMLEFT><TDNUMOUTL>00</TDNUMOUTL><TDLDEPTH>00</TDLDEPTH><TDLFIRSTIN>0</TDLFIRSTIN><TDLNEXTIND>0</TDLNEXTIND><TDLCOUNT>0</TDLCOUNT><TDFAMILY>TIMES</TDFAMILY><TDHEIGHT>080</TDHEIGHT><TDBOLD>*</TDBOLD><TDITALIC>*</TDITALIC><TDUNDERLIN>*</TDUNDERLIN><TDULPOS>0.00</TDULPOS><TDULTHICK>0.00</TDULTHICK><TDULGREY>000</TDULGREY><RED>000</RED><GREEN>000</GREEN><BLUE>000</BLUE><TRANS>000</TRANS><LANGU>E</LANGU><CAPTION>J  TIMES 8</CAPTION></item><item><ACTIVE>A</ACTIVE><STYLENAME>Z6MM001S_STYLE_SF</STYLENAME><TDPARGRAPH>C6</TDPARGRAPH><TDPJUSTIFY>BLOCK</TDPJUSTIFY><TDPLDIST>0.50</TDPLDIST><TDPLDISTU>LN</TDPLDISTU><TDPTOP>0.00</TDPTOP><TDPTOPU>CM</TDPTOPU><TDPBOT>0.00</TDPBOT><TDPBOTU>CM</TDPBOTU><TDPLEFT>0.00</TDPLEFT><TDPLEFTU>CM</TDPLEFTU><TDPRIGHT>0.00</TDPRIGHT><TDPRIGHTU>CM</TDPRIGHTU><TDPENTRY>0.00</TDPENTRY><TDPENTRYU>CM</TDPENTRYU><TDNUMLEFT>0.00</TDNUMLEFT><TDNUMOUTL>00</TDNUMOUTL><TDLDEPTH>00</TDLDEPTH><TDLFIRSTIN>0</TDLFIRSTIN><TDLNEXTIND>0</TDLNEXTIND><TDLCOUNT>0</TDLCOUNT><TDFAMILY>TIMES</TDFAMILY><TDHEIGHT>075</TDHEIGHT><TDBOLD>*</TDBOLD><TDITALIC>*</TDITALIC><TDUNDERLIN>*</TDUNDERLIN><TDULPOS>0.00</TDULPOS><TDULTHICK>0.00</TDULTHICK><TDULGREY>000</TDULGREY><RED>000</RED><GREEN>000</GREEN><BLUE>000</BLUE><TRANS>000</TRANS><LANGU>E</LANGU><CAPTION>J  TIMES 7.5</CAPTION></item><item><ACTIVE>A</ACTIVE><STYLENAME>Z6MM001S_STYLE_SF</STYLENAME><TDPARGRAPH>C7</TDPARGRAPH><TDPJUSTIFY>BLOCK</TDPJUSTIFY><TDPLDIST>0.70</TDPLDIST><TDPLDISTU>LN</TDPLDISTU><TDPTOP>0.00</TDPTOP><TDPTOPU>CM</TDPTOPU><TDPBOT>0.00</TDPBOT><TDPBOTU>CM</TDPBOTU><TDPLEFT>0.00</TDPLEFT><TDPLEFTU>CM</TDPLEFTU><TDPRIGHT>0.00</TDPRIGHT><TDPRIGHTU>CM</TDPRIGHTU><TDPENTRY>0.00</TDPENTRY><TDPENTRYU>CM</TDPENTRYU><TDNUMLEFT>0.00</TDNUMLEFT><TDNUMOUTL>00</TDNUMOUTL><TDLDEPTH>00</TDLDEPTH><TDLFIRSTIN>0</TDLFIRSTIN><TDLNEXTIND>0</TDLNEXTIND><TDLCOUNT>0</TDLCOUNT><TDFAMILY>TIMES</TDFAMILY><TDHEIGHT>060</TDHEIGHT><TDBOLD>*</TDBOLD><TDITALIC>*</TDITALIC><TDUNDERLIN>*</TDUNDERLIN><TDULPOS>0.00</TDULPOS><TDULTHICK>0.00</TDULTHICK><TDULGREY>000</TDULGREY><RED>000</RED><GREEN>000</GREEN><BLUE>000</BLUE><TRANS>000</TRANS><LANGU>E</LANGU><CAPTION>J  TIMES 6</CAPTION></item><item><ACTIVE>A</ACTIVE><STYLENAME>Z6MM001S_STYLE_SF</STYLENAME><TDPARGRAPH>C8</TDPARGRAPH><TDPJUSTIFY>CENTER</TDPJUSTIFY><TDPLDIST>0.70</TDPLDIST><TDPLDISTU>LN</TDPLDISTU><TDPTOP>0.00</TDPTOP><TDPTOPU>CM</TDPTOPU><TDPBOT>0.00</TDPBOT><TDPBOTU>CM</TDPBOTU><TDPLEFT>0.00</TDPLEFT><TDPLEFTU>CM</TDPLEFTU><TDPRIGHT>0.00</TDPRIGHT><TDPRIGHTU>CM</TDPRIGHTU><TDPENTRY>0.00</TDPENTRY><TDPENTRYU>CM</TDPENTRYU><TDNUMLEFT>0.00</TDNUMLEFT><TDNUMOUTL>00</TDNUMOUTL><TDLDEPTH>00</TDLDEPTH><TDLFIRSTIN>0</TDLFIRSTIN><TDLNEXTIND>0</TDLNEXTIND><TDLCOUNT>0</TDLCOUNT><TDFAMILY>TIMES</TDFAMILY><TDHEIGHT>060</TDHEIGHT><TDBOLD>*</TDBOLD><TDITALIC>*</TDITALIC><TDUNDERLIN>*</TDUNDERLIN><TDULPOS>0.00</TDULPOS><TDULTHICK>0.00</TDULTHICK><TDULGREY>000</TDULGREY><RED>000</RED><GREEN>000</GREEN><BLUE>000</BLUE><TRANS>000</TRANS><LANGU>E</LANGU><CAPTION>C  TIMES 6</CAPTION></item><item><ACTIVE>A</ACTIVE><STYLENAME>Z6MM001S_STYLE_SF</STYLENAME><TDPARGRAPH>C9</TDPARGRAPH><TDPJUSTIFY>BLOCK</TDPJUSTIFY><TDPLDIST>0.70</TDPLDIST><TDPLDISTU>LN</TDPLDISTU><TDPTOP>0.00</TDPTOP><TDPTOPU>CM</TDPTOPU><TDPBOT>0.00</TDPBOT><TDPBOTU>CM</TDPBOTU><TDPLEFT>0.00</TDPLEFT><TDPLEFTU>CM</TDPLEFTU><TDPRIGHT>0.00</TDPRIGHT><TDPRIGHTU>CM</TDPRIGHTU><TDPENTRY>0.00</TDPENTRY><TDPENTRYU>CM</TDPENTRYU><TDNUMLEFT>0.00</TDNUMLEFT><TDNUMOUTL>00</TDNUMOUTL><TDLDEPTH>00</TDLDEPTH><TDLFIRSTIN>0</TDLFIRSTIN><TDLNEXTIND>0</TDLNEXTIND><TDLCOUNT>0</TDLCOUNT><TDFAMILY>TIMES</TDFAMILY><TDHEIGHT>080</TDHEIGHT><TDBOLD>*</TDBOLD><TDITALIC>*</TDITALIC><TDUNDERLIN>*</TDUNDERLIN><TDULPOS>0.00</TDULPOS><TDULTHICK>0.00</TDULTHICK><TDULGREY>000</TDULGREY><RED>000</RED><GREEN>000</GREEN><BLUE>000</BLUE><TRANS>000</TRANS><LANGU>E</LANGU><CAPTION>J  TIMES 8</CAPTION></item><item><ACTIVE>A</ACTIVE><STYLENAME>Z6MM001S_STYLE_SF</STYLENAME><TDPARGRAPH>F1</TDPARGRAPH><TDPJUSTIFY>BLOCK</TDPJUSTIFY><TDPLDIST>0.70</TDPLDIST><TDPLDISTU>LN</TDPLDISTU><TDPTOP>0.00</TDPTOP><TDPTOPU>CM</TDPTOPU><TDPBOT>0.00</TDPBOT><TDPBOTU>CM</TDPBOTU><TDPLEFT>0.00</TDPLEFT><TDPLEFTU>CM</TDPLEFTU><TDPRIGHT>0.00</TDPRIGHT><TDPRIGHTU>CM</TDPRIGHTU><TDPENTRY>0.00</TDPENTRY><TDPENTRYU>CM</TDPENTRYU><TDNUMLEFT>0.00</TDNUMLEFT><TDNUMOUTL>00</TDNUMOUTL><TDLDEPTH>00</TDLDEPTH><TDLFIRSTIN>0</TDLFIRSTIN><TDLNEXTIND>0</TDLNEXTIND><TDLCOUNT>0</TDLCOUNT><TDFAMILY>TIMES</TDFAMILY><TDHEIGHT>080</TDHEIGHT><TDBOLD>*</TDBOLD><TDITALIC>*</TDITALIC><TDUNDERLIN>*</TDUNDERLIN><TDULPOS>0.00</TDULPOS><TDULTHICK>0.00</TDULTHICK><TDULGREY>000</TDULGREY><RED>000</RED><GREEN>000</GREEN><BLUE>000</BLUE><TRANS>000</TRANS><LANGU>E</LANGU><CAPTION>Footer LTIMES 8</CAPTION></item><item><ACTIVE>A</ACTIVE><STYLENAME>Z6MM001S_STYLE_SF</STYLENAME><TDPARGRAPH>F2</TDPARGRAPH><TDPJUSTIFY>RIGHT</TDPJUSTIFY><TDPLDIST>1.00</TDPLDIST><TDPLDISTU>LN</TDPLDISTU><TDPTOP>0.00</TDPTOP><TDPTOPU>CM</TDPTOPU><TDPBOT>0.00</TDPBOT><TDPBOTU>CM</TDPBOTU><TDPLEFT>0.00</TDPLEFT><TDPLEFTU>CM</TDPLEFTU><TDPRIGHT>0.00</TDPRIGHT><TDPRIGHTU>CM</TDPRIGHTU><TDPENTRY>0.00</TDPENTRY><TDPENTRYU>CM</TDPENTRYU><TDNUMLEFT>0.00</TDNUMLEFT><TDNUMOUTL>00</TDNUMOUTL><TDLDEPTH>00</TDLDEPTH><TDLFIRSTIN>0</TDLFIRSTIN><TDLNEXTIND>0</TDLNEXTIND><TDLCOUNT>0</TDLCOUNT><TDFAMILY>TIMES</TDFAMILY><TDHEIGHT>080</TDHEIGHT><TDBOLD>*</TDBOLD><TDITALIC>*</TDITALIC><TDUNDERLIN>*</TDUNDERLIN><TDULPOS>0.00</TDULPOS><TDULTHICK>0.00</TDULTHICK><TDULGREY>000</TDULGREY><RED>000</RED><GREEN>000</GREEN><BLUE>000</BLUE><TRANS>000</TRANS><LANGU>E</LANGU><CAPTION>Footer R TIMES 8</CAPTION></item><item><ACTIVE>A</ACTIVE><STYLENAME>Z6MM001S_STYLE_SF</STYLENAME><TDPARGRAPH>F3</TDPARGRAPH><TDPJUSTIFY>CENTER</TDPJUSTIFY><TDPLDIST>1.00</TDPLDIST><TDPLDISTU>LN</TDPLDISTU><TDPTOP>0.00</TDPTOP><TDPTOPU>CM</TDPTOPU><TDPBOT>0.00</TDPBOT><TDPBOTU>CM</TDPBOTU><TDPLEFT>0.00</TDPLEFT><TDPLEFTU>CM</TDPLEFTU><TDPRIGHT>0.00</TDPRIGHT><TDPRIGHTU>CM</TDPRIGHTU><TDPENTRY>0.00</TDPENTRY><TDPENTRYU>CM</TDPENTRYU><TDNUMLEFT>0.00</TDNUMLEFT><TDNUMOUTL>00</TDNUMOUTL><TDLDEPTH>00</TDLDEPTH><TDLFIRSTIN>0</TDLFIRSTIN><TDLNEXTIND>0</TDLNEXTIND><TDLCOUNT>0</TDLCOUNT><TDFAMILY>TIMES</TDFAMILY><TDHEIGHT>080</TDHEIGHT><TDBOLD>*</TDBOLD><TDITALIC>*</TDITALIC><TDUNDERLIN>*</TDUNDERLIN><TDULPOS>0.00</TDULPOS><TDULTHICK>0.00</TDULTHICK><TDULGREY>000</TDULGREY><RED>000</RED><GREEN>000</GREEN><BLUE>000</BLUE><TRANS>000</TRANS><LANGU>E</LANGU><CAPTION>Footer R  8</CAPTION></item><item><ACTIVE>A</ACTIVE><STYLENAME>Z6MM001S_STYLE_SF</STYLENAME><TDPARGRAPH>H1</TDPARGRAPH><TDPJUSTIFY>CENTER</TDPJUSTIFY><TDPLDIST>1.00</TDPLDIST><TDPLDISTU>LN</TDPLDISTU><TDPTOP>0.00</TDPTOP><TDPTOPU>CM</TDPTOPU><TDPBOT>0.00</TDPBOT><TDPBOTU>CM</TDPBOTU><TDPLEFT>0.00</TDPLEFT><TDPLEFTU>CM</TDPLEFTU><TDPRIGHT>0.00</TDPRIGHT><TDPRIGHTU>CM</TDPRIGHTU><TDPENTRY>0.00</TDPENTRY><TDPENTRYU>CM</TDPENTRYU><TDNUMLEFT>0.00</TDNUMLEFT><TDNUMLEFTU>CM</TDNUMLEFTU><TDNUMOUTL>00</TDNUMOUTL><TDLDEPTH>00</TDLDEPTH><TDLFIRSTIN>0</TDLFIRSTIN><TDLNEXTIND>0</TDLNEXTIND><TDLCOUNT>0</TDLCOUNT><TDFAMILY>TIMES</TDFAMILY><TDHEIGHT>160</TDHEIGHT><TDBOLD>X</TDBOLD><TDITALIC>*</TDITALIC><TDUNDERLIN>*</TDUNDERLIN><TDULPOS>0.00</TDULPOS><TDULTHICK>0.00</TDULTHICK><TDULGREY>000</TDULGREY><RED>000</RED><GREEN>000</GREEN><BLUE>000</BLUE><TRANS>000</TRANS><LANGU>E</LANGU><CAPTION>HW Centered Bold TIMES 16</CAPTION></item><item><ACTIVE>A</ACTIVE><STYLENAME>Z6MM001S_STYLE_SF</STYLENAME><TDPARGRAPH>H2</TDPARGRAPH><TDPJUSTIFY>CENTER</TDPJUSTIFY><TDPLDIST>1.00</TDPLDIST><TDPLDISTU>LN</TDPLDISTU><TDPTOP>0.00</TDPTOP><TDPTOPU>CM</TDPTOPU><TDPBOT>0.00</TDPBOT><TDPBOTU>CM</TDPBOTU><TDPLEFT>1.00</TDPLEFT><TDPLEFTU>CM</TDPLEFTU><TDPRIGHT>0.00</TDPRIGHT><TDPRIGHTU>CM</TDPRIGHTU><TDPENTRY>0.00</TDPENTRY><TDPENTRYU>CM</TDPENTRYU><TDNUMLEFT>0.00</TDNUMLEFT><TDNUMLEFTU>CM</TDNUMLEFTU><TDNUMOUTL>00</TDNUMOUTL><TDLDEPTH>00</TDLDEPTH><TDLFIRSTIN>0</TDLFIRSTIN><TDLNEXTIND>0</TDLNEXTIND><TDLCOUNT>0</TDLCOUNT><TDFAMILY>TIMES</TDFAMILY><TDHEIGHT>140</TDHEIGHT><TDBOLD>X</TDBOLD><TDITALIC>*</TDITALIC><TDUNDERLIN>*</TDUNDERLIN><TDULPOS>0.00</TDULPOS><TDULTHICK>0.00</TDULTHICK><TDULGREY>000</TDULGREY><RED>000</RED><GREEN>000</GREEN><BLUE>000</BLUE><TRANS>000</TRANS><LANGU>E</LANGU><CAPTION>HW L1cm TIMES 14 Bold</CAPTION></item><item><ACTIVE>A</ACTIVE><STYLENAME>Z6MM001S_STYLE_SF</STYLENAME><TDPARGRAPH>H3</TDPARGRAPH><TDPJUSTIFY>CENTER</TDPJUSTIFY><TDPLDIST>1.00</TDPLDIST><TDPLDISTU>LN</TDPLDISTU><TDPTOP>0.00</TDPTOP><TDPTOPU>CM</TDPTOPU><TDPBOT>0.00</TDPBOT><TDPBOTU>CM</TDPBOTU><TDPLEFT>0.00</TDPLEFT><TDPLEFTU>CM</TDPLEFTU><TDPRIGHT>0.00</TDPRIGHT><TDPRIGHTU>CM</TDPRIGHTU><TDPENTRY>0.00</TDPENTRY><TDPENTRYU>CM</TDPENTRYU><TDNUMLEFT>0.00</TDNUMLEFT><TDNUMLEFTU>CM</TDNUMLEFTU><TDNUMOUTL>00</TDNUMOUTL><TDLDEPTH>00</TDLDEPTH><TDLFIRSTIN>0</TDLFIRSTIN><TDLNEXTIND>0</TDLNEXTIND><TDLCOUNT>0</TDLCOUNT><TDFAMILY>TIMES</TDFAMILY><TDHEIGHT>240</TDHEIGHT><TDBOLD>X</TDBOLD><TDITALIC>*</TDITALIC><TDUNDERLIN>*</TDUNDERLIN><TDULPOS>0.00</TDULPOS><TDULTHICK>0.00</TDULTHICK><TDULGREY>000</TDULGREY><RED>000</RED><GREEN>000</GREEN><BLUE>000</BLUE><TRANS>000</TRANS><LANGU>E</LANGU><CAPTION>HW Centered Bold TIMES 20</CAPTION></item><item><ACTIVE>A</ACTIVE><STYLENAME>Z6MM001S_STYLE_SF</STYLENAME><TDPARGRAPH>H4</TDPARGRAPH><TDPJUSTIFY>CENTER</TDPJUSTIFY><TDPLDIST>0.60</TDPLDIST><TDPLDISTU>LN</TDPLDISTU><TDPTOP>0.00</TDPTOP><TDPTOPU>CM</TDPTOPU><TDPBOT>0.00</TDPBOT><TDPBOTU>CM</TDPBOTU><TDPLEFT>0.00</TDPLEFT><TDPLEFTU>CM</TDPLEFTU><TDPRIGHT>0.00</TDPRIGHT><TDPRIGHTU>CM</TDPRIGHTU><TDPENTRY>0.00</TDPENTRY><TDPENTRYU>CM</TDPENTRYU><TDNUMLEFT>0.00</TDNUMLEFT><TDNUMLEFTU>CM</TDNUMLEFTU><TDNUMOUTL>00</TDNUMOUTL><TDLDEPTH>00</TDLDEPTH><TDLFIRSTIN>0</TDLFIRSTIN><TDLNEXTIND>0</TDLNEXTIND><TDLCOUNT>0</TDLCOUNT><TDFAMILY>TIMES</TDFAMILY><TDHEIGHT>080</TDHEIGHT><TDBOLD>X</TDBOLD><TDITALIC>*</TDITALIC><TDUNDERLIN>*</TDUNDERLIN><TDULPOS>0.00</TDULPOS><TDULTHICK>0.00</TDULTHICK><TDULGREY>000</TDULGREY><RED>000</RED><GREEN>000</GREEN><BLUE>000</BLUE><TRANS>000</TRANS><LANGU>E</LANGU><CAPTION>HW Centered Bold TIMES 8</CAPTION></item><item><ACTIVE>A</ACTIVE><STYLENAME>Z6MM001S_STYLE_SF</STYLENAME><TDPARGRAPH>H5</TDPARGRAPH><TDPJUSTIFY>CENTER</TDPJUSTIFY><TDPLDIST>1.00</TDPLDIST><TDPLDISTU>LN</TDPLDISTU><TDPTOP>0.00</TDPTOP><TDPTOPU>CM</TDPTOPU><TDPBOT>0.00</TDPBOT><TDPBOTU>CM</TDPBOTU><TDPLEFT>0.00</TDPLEFT><TDPLEFTU>CM</TDPLEFTU><TDPRIGHT>0.00</TDPRIGHT><TDPRIGHTU>CM</TDPRIGHTU><TDPENTRY>0.00</TDPENTRY><TDPENTRYU>CM</TDPENTRYU><TDNUMLEFT>0.00</TDNUMLEFT><TDNUMLEFTU>CM</TDNUMLEFTU><TDNUMOUTL>00</TDNUMOUTL><TDLDEPTH>00</TDLDEPTH><TDLFIRSTIN>0</TDLFIRSTIN><TDLNEXTIND>0</TDLNEXTIND><TDLCOUNT>0</TDLCOUNT><TDFAMILY>TIMES</TDFAMILY><TDHEIGHT>140</TDHEIGHT><TDBOLD>X</TDBOLD><TDITALIC>*</TDITALIC><TDUNDERLIN>*</TDUNDERLIN><TDULPOS>0.00</TDULPOS><TDULTHICK>0.00</TDULTHICK><TDULGREY>000</TDULGREY><RED>000</RED><GREEN>000</GREEN><BLUE>000</BLUE><TRANS>000</TRANS><LANGU>E</LANGU><CAPTION>HW Centered Bold TIMES 16</CAPTION></item><item><ACTIVE>A</ACTIVE><STYLENAME>Z6MM001S_STYLE_SF</STYLENAME><TDPARGRAPH>HW</TDPARGRAPH><TDPJUSTIFY>CENTER</TDPJUSTIFY><TDPLDIST>1.00</TDPLDIST><TDPLDISTU>LN</TDPLDISTU><TDPTOP>0.00</TDPTOP><TDPTOPU>CM</TDPTOPU><TDPBOT>0.00</TDPBOT><TDPBOTU>CM</TDPBOTU><TDPLEFT>1.00</TDPLEFT><TDPLEFTU>CM</TDPLEFTU><TDPRIGHT>0.00</TDPRIGHT><TDPRIGHTU>CM</TDPRIGHTU><TDPENTRY>0.00</TDPENTRY><TDPENTRYU>CM</TDPENTRYU><TDNUMLEFT>0.00</TDNUMLEFT><TDNUMLEFTU>CM</TDNUMLEFTU><TDNUMOUTL>00</TDNUMOUTL><TDLDEPTH>00</TDLDEPTH><TDLFIRSTIN>0</TDLFIRSTIN><TDLNEXTIND>0</TDLNEXTIND><TDLCOUNT>0</TDLCOUNT><TDFAMILY>TIMES</TDFAMILY><TDHEIGHT>130</TDHEIGHT><TDBOLD>*</TDBOLD><TDITALIC>*</TDITALIC><TDUNDERLIN>*</TDUNDERLIN><TDULPOS>0.00</TDULPOS><TDULTHICK>0.00</TDULTHICK><TDULGREY>000</TDULGREY><RED>000</RED><GREEN>000</GREEN><BLUE>000</BLUE><TRANS>000</TRANS><LANGU>E</LANGU><CAPTION>HW 1cm L 13 TIMES</CAPTION></item><item><ACTIVE>A</ACTIVE><STYLENAME>Z6MM001S_STYLE_SF</STYLENAME><TDPARGRAPH>L0</TDPARGRAPH><TDPJUSTIFY>LEFT</TDPJUSTIFY><TDPLDIST>1.00</TDPLDIST><TDPLDISTU>LN</TDPLDISTU><TDPTOP>0.00</TDPTOP><TDPTOPU>CM</TDPTOPU><TDPBOT>0.00</TDPBOT><TDPBOTU>CM</TDPBOTU><TDPLEFT>0.00</TDPLEFT><TDPLEFTU>CM</TDPLEFTU><TDPRIGHT>0.00</TDPRIGHT><TDPRIGHTU>CM</TDPRIGHTU><TDPENTRY>0.00</TDPENTRY><TDPENTRYU>CM</TDPENTRYU><TDNUMLEFT>0.00</TDNUMLEFT><TDNUMLEFTU>CM</TDNUMLEFTU><TDNUMOUTL>00</TDNUMOUTL><TDLDEPTH>00</TDLDEPTH><TDLFIRSTIN>0</TDLFIRSTIN><TDLNEXTIND>0</TDLNEXTIND><TDLCOUNT>0</TDLCOUNT><TDFAMILY>TIMES</TDFAMILY><TDHEIGHT>070</TDHEIGHT><TDBOLD>*</TDBOLD><TDITALIC>*</TDITALIC><TDUNDERLIN>*</TDUNDERLIN><TDULPOS>0.00</TDULPOS><TDULTHICK>0.00</TDULTHICK><TDULGREY>000</TDULGREY><RED>000</RED><GREEN>000</GREEN><BLUE>000</BLUE><TRANS>000</TRANS><LANGU>E</LANGU><CAPTION>L Times 7</CAPTION></item><item><ACTIVE>A</ACTIVE><STYLENAME>Z6MM001S_STYLE_SF</STYLENAME><TDPARGRAPH>L1</TDPARGRAPH><TDPJUSTIFY>BLOCK</TDPJUSTIFY><TDPLDIST>1.00</TDPLDIST><TDPLDISTU>LN</TDPLDISTU><TDPTOP>0.00</TDPTOP><TDPTOPU>CM</TDPTOPU><TDPBOT>0.00</TDPBOT><TDPBOTU>CM</TDPBOTU><TDPLEFT>0.00</TDPLEFT><TDPLEFTU>CM</TDPLEFTU><TDPRIGHT>0.00</TDPRIGHT><TDPRIGHTU>CM</TDPRIGHTU><TDPENTRY>0.00</TDPENTRY><TDPENTRYU>CM</TDPENTRYU><TDNUMLEFT>0.00</TDNUMLEFT><TDNUMOUTL>00</TDNUMOUTL><TDLDEPTH>00</TDLDEPTH><TDLFIRSTIN>0</TDLFIRSTIN><TDLNEXTIND>0</TDLNEXTIND><TDLCOUNT>0</TDLCOUNT><TDFAMILY>TIMES</TDFAMILY><TDHEIGHT>100</TDHEIGHT><TDBOLD>*</TDBOLD><TDITALIC>*</TDITALIC><TDUNDERLIN>*</TDUNDERLIN><TDULPOS>0.00</TDULPOS><TDULTHICK>0.00</TDULTHICK><TDULGREY>000</TDULGREY><RED>000</RED><GREEN>000</GREEN><BLUE>000</BLUE><TRANS>000</TRANS><LANGU>E</LANGU><CAPTION>L  TIMES 10 (Left al)</CAPTION></item><item><ACTIVE>A</ACTIVE><STYLENAME>Z6MM001S_STYLE_SF</STYLENAME><TDPARGRAPH>L2</TDPARGRAPH><TDPJUSTIFY>BLOCK</TDPJUSTIFY><TDPLDIST>1.00</TDPLDIST><TDPLDISTU>LN</TDPLDISTU><TDPTOP>0.00</TDPTOP><TDPTOPU>CM</TDPTOPU><TDPBOT>0.00</TDPBOT><TDPBOTU>CM</TDPBOTU><TDPLEFT>0.00</TDPLEFT><TDPLEFTU>CM</TDPLEFTU><TDPRIGHT>0.00</TDPRIGHT><TDPRIGHTU>CM</TDPRIGHTU><TDPENTRY>0.00</TDPENTRY><TDPENTRYU>CM</TDPENTRYU><TDNUMLEFT>0.00</TDNUMLEFT><TDNUMOUTL>00</TDNUMOUTL><TDLDEPTH>00</TDLDEPTH><TDLFIRSTIN>0</TDLFIRSTIN><TDLNEXTIND>0</TDLNEXTIND><TDLCOUNT>0</TDLCOUNT><TDFAMILY>TIMES</TDFAMILY><TDHEIGHT>120</TDHEIGHT><TDBOLD>*</TDBOLD><TDITALIC>*</TDITALIC><TDUNDERLIN>*</TDUNDERLIN><TDULPOS>0.00</TDULPOS><TDULTHICK>0.00</TDULTHICK><TDULGREY>000</TDULGREY><RED>000</RED><GREEN>000</GREEN><BLUE>000</BLUE><TRANS>000</TRANS><LANGU>E</LANGU><CAPTION>L TIMES 12</CAPTION></item><item><ACTIVE>A</ACTIVE><STYLENAME>Z6MM001S_STYLE_SF</STYLENAME><TDPARGRAPH>L3</TDPARGRAPH><TDPJUSTIFY>BLOCK</TDPJUSTIFY><TDPLDIST>1.00</TDPLDIST><TDPLDISTU>LN</TDPLDISTU><TDPTOP>0.00</TDPTOP><TDPTOPU>CM</TDPTOPU><TDPBOT>0.00</TDPBOT><TDPBOTU>CM</TDPBOTU><TDPLEFT>0.00</TDPLEFT><TDPLEFTU>CM</TDPLEFTU><TDPRIGHT>0.00</TDPRIGHT><TDPRIGHTU>CM</TDPRIGHTU><TDPENTRY>0.00</TDPENTRY><TDPENTRYU>CM</TDPENTRYU><TDNUMLEFT>0.00</TDNUMLEFT><TDNUMOUTL>00</TDNUMOUTL><TDLDEPTH>00</TDLDEPTH><TDLFIRSTIN>0</TDLFIRSTIN><TDLNEXTIND>0</TDLNEXTIND><TDLCOUNT>0</TDLCOUNT><TDFAMILY>TIMES</TDFAMILY><TDHEIGHT>160</TDHEIGHT><TDBOLD>*</TDBOLD><TDITALIC>*</TDITALIC><TDUNDERLIN>*</TDUNDERLIN><TDULPOS>0.00</TDULPOS><TDULTHICK>0.00</TDULTHICK><TDULGREY>000</TDULGREY><RED>000</RED><GREEN>000</GREEN><BLUE>000</BLUE><TRANS>000</TRANS><LANGU>E</LANGU><CAPTION>L  TIMES 14 (Left al)</CAPTION></item><item><ACTIVE>A</ACTIVE><STYLENAME>Z6MM001S_STYLE_SF</STYLENAME><TDPARGRAPH>L4</TDPARGRAPH><TDPJUSTIFY>LEFT</TDPJUSTIFY><TDPLDIST>1.00</TDPLDIST><TDPLDISTU>LN</TDPLDISTU><TDPTOP>0.00</TDPTOP><TDPTOPU>CM</TDPTOPU><TDPBOT>0.00</TDPBOT><TDPBOTU>CM</TDPBOTU><TDPLEFT>0.00</TDPLEFT><TDPLEFTU>CM</TDPLEFTU><TDPRIGHT>0.00</TDPRIGHT><TDPRIGHTU>CM</TDPRIGHTU><TDPENTRY>0.00</TDPENTRY><TDPENTRYU>CM</TDPENTRYU><TDNUMLEFT>0.00</TDNUMLEFT><TDNUMLEFTU>CM</TDNUMLEFTU><TDNUMOUTL>00</TDNUMOUTL><TDLDEPTH>00</TDLDEPTH><TDLFIRSTIN>0</TDLFIRSTIN><TDLNEXTIND>0</TDLNEXTIND><TDLCOUNT>0</TDLCOUNT><TDFAMILY>TIMES</TDFAMILY><TDHEIGHT>080</TDHEIGHT><TDBOLD>*</TDBOLD><TDITALIC>*</TDITALIC><TDUNDERLIN>*</TDUNDERLIN><TDULPOS>0.00</TDULPOS><TDULTHICK>0.00</TDULTHICK><TDULGREY>000</TDULGREY><RED>000</RED><GREEN>000</GREEN><BLUE>000</BLUE><TRANS>000</TRANS><LANGU>E</LANGU><CAPTION>L Times 8</CAPTION></item><item><ACTIVE>A</ACTIVE><STYLENAME>Z6MM001S_STYLE_SF</STYLENAME><TDPARGRAPH>L5</TDPARGRAPH><TDPJUSTIFY>LEFT</TDPJUSTIFY><TDPLDIST>1.00</TDPLDIST><TDPLDISTU>LN</TDPLDISTU><TDPTOP>0.00</TDPTOP><TDPTOPU>CM</TDPTOPU><TDPBOT>0.00</TDPBOT><TDPBOTU>CM</TDPBOTU><TDPLEFT>1.00</TDPLEFT><TDPLEFTU>MM</TDPLEFTU><TDPRIGHT>0.00</TDPRIGHT><TDPRIGHTU>CM</TDPRIGHTU><TDPENTRY>0.00</TDPENTRY><TDPENTRYU>CM</TDPENTRYU><TDNUMLEFT>0.00</TDNUMLEFT><TDNUMOUTL>00</TDNUMOUTL><TDLDEPTH>00</TDLDEPTH><TDLFIRSTIN>0</TDLFIRSTIN><TDLNEXTIND>0</TDLNEXTIND><TDLCOUNT>0</TDLCOUNT><TDFAMILY>TIMES</TDFAMILY><TDHEIGHT>100</TDHEIGHT><TDBOLD>*</TDBOLD><TDITALIC>*</TDITALIC><TDUNDERLIN>*</TDUNDERLIN><TDULPOS>0.00</TDULPOS><TDULTHICK>0.00</TDULTHICK><TDULGREY>000</TDULGREY><RED>000</RED><GREEN>000</GREEN><BLUE>000</BLUE><TRANS>000</TRANS><LANGU>E</LANGU><CAPTION>L  TIMES 10 (Left al)</CAPTION></item><item><ACTIVE>A</ACTIVE><STYLENAME>Z6MM001S_STYLE_SF</STYLENAME><TDPARGRAPH>L6</TDPARGRAPH><TDPJUSTIFY>LEFT</TDPJUSTIFY><TDPLDIST>1.00</TDPLDIST><TDPLDISTU>LN</TDPLDISTU><TDPTOP>0.00</TDPTOP><TDPTOPU>CM</TDPTOPU><TDPBOT>0.00</TDPBOT><TDPBOTU>CM</TDPBOTU><TDPLEFT>0.00</TDPLEFT><TDPLEFTU>CM</TDPLEFTU><TDPRIGHT>0.00</TDPRIGHT><TDPRIGHTU>CM</TDPRIGHTU><TDPENTRY>0.20</TDPENTRY><TDPENTRYU>CM</TDPENTRYU><TDNUMLEFT>0.00</TDNUMLEFT><TDNUMLEFTU>CM</TDNUMLEFTU><TDNUMOUTL>00</TDNUMOUTL><TDLDEPTH>00</TDLDEPTH><TDLFIRSTIN>0</TDLFIRSTIN><TDLNEXTIND>0</TDLNEXTIND><TDLCOUNT>0</TDLCOUNT><TDFAMILY>TIMES</TDFAMILY><TDHEIGHT>080</TDHEIGHT><TDBOLD>*</TDBOLD><TDITALIC>*</TDITALIC><TDUNDERLIN>*</TDUNDERLIN><TDULPOS>0.00</TDULPOS><TDULTHICK>0.00</TDULTHICK><TDULGREY>000</TDULGREY><RED>000</RED><GREEN>000</GREEN><BLUE>000</BLUE><TRANS>000</TRANS><LANGU>E</LANGU><CAPTION>L Times 8</CAPTION></item><item><ACTIVE>A</ACTIVE><STYLENAME>Z6MM001S_STYLE_SF</STYLENAME><TDPARGRAPH>L7</TDPARGRAPH><TDPJUSTIFY>LEFT</TDPJUSTIFY><TDPLDIST>0.70</TDPLDIST><TDPLDISTU>LN</TDPLDISTU><TDPTOP>0.05</TDPTOP><TDPTOPU>MM</TDPTOPU><TDPBOT>0.00</TDPBOT><TDPBOTU>CM</TDPBOTU><TDPLEFT>0.00</TDPLEFT><TDPLEFTU>CM</TDPLEFTU><TDPRIGHT>0.00</TDPRIGHT><TDPRIGHTU>CM</TDPRIGHTU><TDPENTRY>0.20</TDPENTRY><TDPENTRYU>CM</TDPENTRYU><TDNUMLEFT>0.00</TDNUMLEFT><TDNUMOUTL>00</TDNUMOUTL><TDLDEPTH>00</TDLDEPTH><TDLFIRSTIN>0</TDLFIRSTIN><TDLNEXTIND>0</TDLNEXTIND><TDLCOUNT>0</TDLCOUNT><TDFAMILY>TIMES</TDFAMILY><TDHEIGHT>080</TDHEIGHT><TDBOLD>*</TDBOLD><TDITALIC>*</TDITALIC><TDUNDERLIN>*</TDUNDERLIN><TDULPOS>0.00</TDULPOS><TDULTHICK>0.00</TDULTHICK><TDULGREY>000</TDULGREY><RED>000</RED><GREEN>000</GREEN><BLUE>000</BLUE><TRANS>000</TRANS><LANGU>E</LANGU><CAPTION>L Times 8 New</CAPTION></item><item><ACTIVE>A</ACTIVE><STYLENAME>Z6MM001S_STYLE_SF</STYLENAME><TDPARGRAPH>L8</TDPARGRAPH><TDPJUSTIFY>LEFT</TDPJUSTIFY><TDPLDIST>0.60</TDPLDIST><TDPLDISTU>LN</TDPLDISTU><TDPTOP>0.05</TDPTOP><TDPTOPU>MM</TDPTOPU><TDPBOT>0.00</TDPBOT><TDPBOTU>CM</TDPBOTU><TDPLEFT>0.00</TDPLEFT><TDPLEFTU>CM</TDPLEFTU><TDPRIGHT>0.00</TDPRIGHT><TDPRIGHTU>CM</TDPRIGHTU><TDPENTRY>0.20</TDPENTRY><TDPENTRYU>CM</TDPENTRYU><TDNUMLEFT>0.00</TDNUMLEFT><TDNUMOUTL>00</TDNUMOUTL><TDLDEPTH>00</TDLDEPTH><TDLFIRSTIN>0</TDLFIRSTIN><TDLNEXTIND>0</TDLNEXTIND><TDLCOUNT>0</TDLCOUNT><TDFAMILY>TIMES</TDFAMILY><TDHEIGHT>080</TDHEIGHT><TDBOLD>*</TDBOLD><TDITALIC>*</TDITALIC><TDUNDERLIN>*</TDUNDERLIN><TDULPOS>0.00</TDULPOS><TDULTHICK>0.00</TDULTHICK><TDULGREY>000</TDULGREY><RED>000</RED><GREEN>000</GREEN><BLUE>000</BLUE><TRANS>000</TRANS><LANGU>E</LANGU><CAPTION>L Times 8 New</CAPTION></item><item><ACTIVE>A</ACTIVE><STYLENAME>Z6MM001S_STYLE_SF</STYLENAME><TDPARGRAPH>L9</TDPARGRAPH><TDPJUSTIFY>BLOCK</TDPJUSTIFY><TDPLDIST>1.00</TDPLDIST><TDPLDISTU>LN</TDPLDISTU><TDPTOP>0.00</TDPTOP><TDPTOPU>CM</TDPTOPU><TDPBOT>0.00</TDPBOT><TDPBOTU>CM</TDPBOTU><TDPLEFT>0.00</TDPLEFT><TDPLEFTU>CM</TDPLEFTU><TDPRIGHT>0.00</TDPRIGHT><TDPRIGHTU>CM</TDPRIGHTU><TDPENTRY>0.00</TDPENTRY><TDPENTRYU>CM</TDPENTRYU><TDNUMLEFT>0.00</TDNUMLEFT><TDNUMOUTL>00</TDNUMOUTL><TDLDEPTH>00</TDLDEPTH><TDLFIRSTIN>0</TDLFIRSTIN><TDLNEXTIND>0</TDLNEXTIND><TDLCOUNT>0</TDLCOUNT><TDFAMILY>TIMES</TDFAMILY><TDHEIGHT>115</TDHEIGHT><TDBOLD>*</TDBOLD><TDITALIC>*</TDITALIC><TDUNDERLIN>*</TDUNDERLIN><TDULPOS>0.00</TDULPOS><TDULTHICK>0.00</TDULTHICK><TDULGREY>000</TDULGREY><RED>000</RED><GREEN>000</GREEN><BLUE>000</BLUE><TRANS>000</TRANS><LANGU>E</LANGU><CAPTION>L TIMES 11</CAPTION></item><item><ACTIVE>A</ACTIVE><STYLENAME>Z6MM001S_STYLE_SF</STYLENAME><TDPARGRAPH>R1</TDPARGRAPH><TDPJUSTIFY>RIGHT</TDPJUSTIFY><TDPLDIST>1.00</TDPLDIST><TDPLDISTU>LN</TDPLDISTU><TDPTOP>0.00</TDPTOP><TDPTOPU>CM</TDPTOPU><TDPBOT>0.00</TDPBOT><TDPBOTU>CM</TDPBOTU><TDPLEFT>0.00</TDPLEFT><TDPLEFTU>CM</TDPLEFTU><TDPRIGHT>1.00</TDPRIGHT><TDPRIGHTU>MM</TDPRIGHTU><TDPENTRY>0.00</TDPENTRY><TDPENTRYU>CM</TDPENTRYU><TDNUMLEFT>0.00</TDNUMLEFT><TDNUMLEFTU>CM</TDNUMLEFTU><TDNUMOUTL>00</TDNUMOUTL><TDLDEPTH>00</TDLDEPTH><TDLFIRSTIN>0</TDLFIRSTIN><TDLNEXTIND>0</TDLNEXTIND><TDLCOUNT>0</TDLCOUNT><TDFAMILY>TIMES</TDFAMILY><TDHEIGHT>100</TDHEIGHT><TDBOLD>*</TDBOLD><TDITALIC>*</TDITALIC><TDUNDERLIN>*</TDUNDERLIN><TDULPOS>0.00</TDULPOS><TDULTHICK>0.00</TDULTHICK><TDULGREY>000</TDULGREY><RED>000</RED><GREEN>000</GREEN><BLUE>000</BLUE><TRANS>000</TRANS><LANGU>E</LANGU><CAPTION>R  TIMES 10</CAPTION></item><item><ACTIVE>A</ACTIVE><STYLENAME>Z6MM001S_STYLE_SF</STYLENAME><TDPARGRAPH>R2</TDPARGRAPH><TDPJUSTIFY>RIGHT</TDPJUSTIFY><TDPLDIST>1.00</TDPLDIST><TDPLDISTU>LN</TDPLDISTU><TDPTOP>0.00</TDPTOP><TDPTOPU>CM</TDPTOPU><TDPBOT>0.00</TDPBOT><TDPBOTU>CM</TDPBOTU><TDPLEFT>0.00</TDPLEFT><TDPLEFTU>CM</TDPLEFTU><TDPRIGHT>0.00</TDPRIGHT><TDPRIGHTU>CM</TDPRIGHTU><TDPENTRY>0.00</TDPENTRY><TDPENTRYU>CM</TDPENTRYU><TDNUMLEFT>0.00</TDNUMLEFT><TDNUMOUTL>00</TDNUMOUTL><TDLDEPTH>00</TDLDEPTH><TDLFIRSTIN>0</TDLFIRSTIN><TDLNEXTIND>0</TDLNEXTIND><TDLCOUNT>0</TDLCOUNT><TDFAMILY>TIMES</TDFAMILY><TDHEIGHT>100</TDHEIGHT><TDBOLD>X</TDBOLD><TDITALIC>*</TDITALIC><TDUNDERLIN>*</TDUNDERLIN><TDULPOS>0.00</TDULPOS><TDULTHICK>0.00</TDULTHICK><TDULGREY>000</TDULGREY><RED>000</RED><GREEN>000</GREEN><BLUE>000</BLUE><TRANS>000</TRANS><LANGU>E</LANGU><CAPTION>R TIMES 10 Bold</CAPTION></item><item><ACTIVE>A</ACTIVE><STYLENAME>Z6MM001S_STYLE_SF</STYLENAME><TDPARGRAPH>R3</TDPARGRAPH><TDPJUSTIFY>RIGHT</TDPJUSTIFY><TDPLDIST>1.00</TDPLDIST><TDPLDISTU>LN</TDPLDISTU><TDPTOP>0.00</TDPTOP><TDPTOPU>CM</TDPTOPU><TDPBOT>0.00</TDPBOT><TDPBOTU>CM</TDPBOTU><TDPLEFT>0.00</TDPLEFT><TDPLEFTU>CM</TDPLEFTU><TDPRIGHT>0.00</TDPRIGHT><TDPRIGHTU>CM</TDPRIGHTU><TDPENTRY>0.00</TDPENTRY><TDPENTRYU>CM</TDPENTRYU><TDNUMLEFT>0.00</TDNUMLEFT><TDNUMLEFTU>CM</TDNUMLEFTU><TDNUMOUTL>00</TDNUMOUTL><TDLDEPTH>00</TDLDEPTH><TDLFIRSTIN>0</TDLFIRSTIN><TDLNEXTIND>0</TDLNEXTIND><TDLCOUNT>0</TDLCOUNT><TDFAMILY>TIMES</TDFAMILY><TDHEIGHT>080</TDHEIGHT><TDBOLD>*</TDBOLD><TDITALIC>*</TDITALIC><TDUNDERLIN>*</TDUNDERLIN><TDULPOS>0.00</TDULPOS><TDULTHICK>0.00</TDULTHICK><TDULGREY>000</TDULGREY><RED>000</RED><GREEN>000</GREEN><BLUE>000</BLUE><TRANS>000</TRANS><LANGU>E</LANGU><CAPTION>R Times 8</CAPTION></item><item><ACTIVE>A</ACTIVE><STYLENAME>Z6MM001S_STYLE_SF</STYLENAME><TDPARGRAPH>R4</TDPARGRAPH><TDPJUSTIFY>RIGHT</TDPJUSTIFY><TDPLDIST>1.50</TDPLDIST><TDPLDISTU>LN</TDPLDISTU><TDPTOP>0.00</TDPTOP><TDPTOPU>CM</TDPTOPU><TDPBOT>0.00</TDPBOT><TDPBOTU>CM</TDPBOTU><TDPLEFT>0.00</TDPLEFT><TDPLEFTU>CM</TDPLEFTU><TDPRIGHT>0.00</TDPRIGHT><TDPRIGHTU>CM</TDPRIGHTU><TDPENTRY>0.00</TDPENTRY><TDPENTRYU>CM</TDPENTRYU><TDNUMLEFT>0.00</TDNUMLEFT><TDNUMLEFTU>CM</TDNUMLEFTU><TDNUMOUTL>00</TDNUMOUTL><TDLDEPTH>00</TDLDEPTH><TDLFIRSTIN>0</TDLFIRSTIN><TDLNEXTIND>0</TDLNEXTIND><TDLCOUNT>0</TDLCOUNT><TDFAMILY>TIMES</TDFAMILY><TDHEIGHT>100</TDHEIGHT><TDBOLD>*</TDBOLD><TDITALIC>*</TDITALIC><TDUNDERLIN>*</TDUNDERLIN><TDULPOS>0.00</TDULPOS><TDULTHICK>0.00</TDULTHICK><TDULGREY>000</TDULGREY><RED>000</RED><GREEN>000</GREEN><BLUE>000</BLUE><TRANS>000</TRANS><LANGU>E</LANGU><CAPTION>R  TIMES 10 line spcae 1.5</CAPTION></item><item><ACTIVE>A</ACTIVE><STYLENAME>Z6MM001S_STYLE_SF</STYLENAME><TDPARGRAPH>R5</TDPARGRAPH><TDPJUSTIFY>RIGHT</TDPJUSTIFY><TDPLDIST>1.00</TDPLDIST><TDPLDISTU>LN</TDPLDISTU><TDPTOP>0.00</TDPTOP><TDPTOPU>CM</TDPTOPU><TDPBOT>0.00</TDPBOT><TDPBOTU>CM</TDPBOTU><TDPLEFT>0.00</TDPLEFT><TDPLEFTU>CM</TDPLEFTU><TDPRIGHT>0.00</TDPRIGHT><TDPRIGHTU>CM</TDPRIGHTU><TDPENTRY>0.00</TDPENTRY><TDPENTRYU>CM</TDPENTRYU><TDNUMLEFT>0.00</TDNUMLEFT><TDNUMLEFTU>CM</TDNUMLEFTU><TDNUMOUTL>00</TDNUMOUTL><TDLDEPTH>00</TDLDEPTH><TDLFIRSTIN>0</TDLFIRSTIN><TDLNEXTIND>0</TDLNEXTIND><TDLCOUNT>0</TDLCOUNT><TDFAMILY>TIMES</TDFAMILY><TDHEIGHT>070</TDHEIGHT><TDBOLD>*</TDBOLD><TDITALIC>*</TDITALIC><TDUNDERLIN>*</TDUNDERLIN><TDULPOS>0.00</TDULPOS><TDULTHICK>0.00</TDULTHICK><TDULGREY>000</TDULGREY><RED>000</RED><GREEN>000</GREEN><BLUE>000</BLUE><TRANS>000</TRANS><LANGU>E</LANGU><CAPTION>R Times 7</CAPTION></item><item><ACTIVE>A</ACTIVE><STYLENAME>Z6MM001S_STYLE_SF</STYLENAME><TDPARGRAPH>S1</TDPARGRAPH><TDPJUSTIFY>BLOCK</TDPJUSTIFY><TDPLDIST>0.70</TDPLDIST><TDPLDISTU>LN</TDPLDISTU><TDPTOP>0.00</TDPTOP><TDPTOPU>CM</TDPTOPU><TDPBOT>0.00</TDPBOT><TDPBOTU>CM</TDPBOTU><TDPLEFT>0.00</TDPLEFT><TDPLEFTU>CM</TDPLEFTU><TDPRIGHT>0.00</TDPRIGHT><TDPRIGHTU>CM</TDPRIGHTU><TDPENTRY>0.00</TDPENTRY><TDPENTRYU>CM</TDPENTRYU><TDNUMLEFT>0.00</TDNUMLEFT><TDNUMOUTL>00</TDNUMOUTL><TDLDEPTH>00</TDLDEPTH><TDLFIRSTIN>0</TDLFIRSTIN><TDLNEXTIND>0</TDLNEXTIND><TDLCOUNT>0</TDLCOUNT><TDFAMILY>TIMES</TDFAMILY><TDHEIGHT>070</TDHEIGHT><TDBOLD>*</TDBOLD><TDITALIC>*</TDITALIC><TDUNDERLIN>*</TDUNDERLIN><TDULPOS>0.00</TDULPOS><TDULTHICK>0.00</TDULTHICK><TDULGREY>000</TDULGREY><RED>000</RED><GREEN>000</GREEN><BLUE>000</BLUE><TRANS>000</TRANS><LANGU>E</LANGU><CAPTION>Footer LTIMES 7</CAPTION></item><item><ACTIVE>A</ACTIVE><STYLENAME>Z6MM001S_STYLE_SF</STYLENAME><TDPARGRAPH>S2</TDPARGRAPH><TDPJUSTIFY>BLOCK</TDPJUSTIFY><TDPLDIST>0.70</TDPLDIST><TDPLDISTU>LN</TDPLDISTU><TDPTOP>0.00</TDPTOP><TDPTOPU>CM</TDPTOPU><TDPBOT>0.00</TDPBOT><TDPBOTU>CM</TDPBOTU><TDPLEFT>0.00</TDPLEFT><TDPLEFTU>CM</TDPLEFTU><TDPRIGHT>0.00</TDPRIGHT><TDPRIGHTU>CM</TDPRIGHTU><TDPENTRY>0.00</TDPENTRY><TDPENTRYU>CM</TDPENTRYU><TDNUMLEFT>0.00</TDNUMLEFT><TDNUMOUTL>00</TDNUMOUTL><TDLDEPTH>00</TDLDEPTH><TDLFIRSTIN>0</TDLFIRSTIN><TDLNEXTIND>0</TDLNEXTIND><TDLCOUNT>0</TDLCOUNT><TDFAMILY>TIMES</TDFAMILY><TDHEIGHT>080</TDHEIGHT><TDBOLD>*</TDBOLD><TDITALIC>*</TDITALIC><TDUNDERLIN>*</TDUNDERLIN><TDULPOS>0.00</TDULPOS><TDULTHICK>0.00</TDULTHICK><TDULGREY>000</TDULGREY><RED>000</RED><GREEN>000</GREEN><BLUE>000</BLUE><TRANS>000</TRANS><LANGU>E</LANGU><CAPTION>Footer LTIMES 8</CAPTION></item><item><ACTIVE>A</ACTIVE><STYLENAME>Z6MM001S_STYLE_SF</STYLENAME><TDPARGRAPH>S3</TDPARGRAPH><TDPJUSTIFY>BLOCK</TDPJUSTIFY><TDPLDIST>0.70</TDPLDIST><TDPLDISTU>LN</TDPLDISTU><TDPTOP>0.00</TDPTOP><TDPTOPU>CM</TDPTOPU><TDPBOT>0.00</TDPBOT><TDPBOTU>CM</TDPBOTU><TDPLEFT>0.00</TDPLEFT><TDPLEFTU>CM</TDPLEFTU><TDPRIGHT>0.00</TDPRIGHT><TDPRIGHTU>CM</TDPRIGHTU><TDPENTRY>0.00</TDPENTRY><TDPENTRYU>CM</TDPENTRYU><TDNUMLEFT>0.00</TDNUMLEFT><TDNUMOUTL>00</TDNUMOUTL><TDLDEPTH>00</TDLDEPTH><TDLFIRSTIN>0</TDLFIRSTIN><TDLNEXTIND>0</TDLNEXTIND><TDLCOUNT>0</TDLCOUNT><TDFAMILY>TIMES</TDFAMILY><TDHEIGHT>050</TDHEIGHT><TDBOLD>*</TDBOLD><TDITALIC>*</TDITALIC><TDUNDERLIN>*</TDUNDERLIN><TDULPOS>0.00</TDULPOS><TDULTHICK>0.00</TDULTHICK><TDULGREY>000</TDULGREY><RED>000</RED><GREEN>000</GREEN><BLUE>000</BLUE><TRANS>000</TRANS><LANGU>E</LANGU><CAPTION>Footer LTIMES 5</CAPTION></item><item><ACTIVE>A</ACTIVE><STYLENAME>Z6MM001S_STYLE_SF</STYLENAME><TDPARGRAPH>S4</TDPARGRAPH><TDPJUSTIFY>BLOCK</TDPJUSTIFY><TDPLDIST>0.70</TDPLDIST><TDPLDISTU>LN</TDPLDISTU><TDPTOP>0.00</TDPTOP><TDPTOPU>CM</TDPTOPU><TDPBOT>0.00</TDPBOT><TDPBOTU>CM</TDPBOTU><TDPLEFT>0.00</TDPLEFT><TDPLEFTU>CM</TDPLEFTU><TDPRIGHT>0.00</TDPRIGHT><TDPRIGHTU>CM</TDPRIGHTU><TDPENTRY>0.00</TDPENTRY><TDPENTRYU>CM</TDPENTRYU><TDNUMLEFT>0.00</TDNUMLEFT><TDNUMOUTL>00</TDNUMOUTL><TDLDEPTH>00</TDLDEPTH><TDLFIRSTIN>0</TDLFIRSTIN><TDLNEXTIND>0</TDLNEXTIND><TDLCOUNT>0</TDLCOUNT><TDFAMILY>TIMES</TDFAMILY><TDHEIGHT>090</TDHEIGHT><TDBOLD>*</TDBOLD><TDITALIC>*</TDITALIC><TDUNDERLIN>*</TDUNDERLIN><TDULPOS>0.00</TDULPOS><TDULTHICK>0.00</TDULTHICK><TDULGREY>000</TDULGREY><RED>000</RED><GREEN>000</GREEN><BLUE>000</BLUE><TRANS>000</TRANS><LANGU>E</LANGU><CAPTION>Footer LTIMES 9</CAPTION></item><item><ACTIVE>A</ACTIVE><STYLENAME>Z6MM001S_STYLE_SF</STYLENAME><TDPARGRAPH>S5</TDPARGRAPH><TDPJUSTIFY>BLOCK</TDPJUSTIFY><TDPLDIST>0.60</TDPLDIST><TDPLDISTU>LN</TDPLDISTU><TDPTOP>0.00</TDPTOP><TDPTOPU>CM</TDPTOPU><TDPBOT>0.00</TDPBOT><TDPBOTU>CM</TDPBOTU><TDPLEFT>0.00</TDPLEFT><TDPLEFTU>CM</TDPLEFTU><TDPRIGHT>0.00</TDPRIGHT><TDPRIGHTU>CM</TDPRIGHTU><TDPENTRY>0.00</TDPENTRY><TDPENTRYU>CM</TDPENTRYU><TDNUMLEFT>0.00</TDNUMLEFT><TDNUMOUTL>00</TDNUMOUTL><TDLDEPTH>00</TDLDEPTH><TDLFIRSTIN>0</TDLFIRSTIN><TDLNEXTIND>0</TDLNEXTIND><TDLCOUNT>0</TDLCOUNT><TDFAMILY>TIMES</TDFAMILY><TDHEIGHT>050</TDHEIGHT><TDBOLD>*</TDBOLD><TDITALIC>*</TDITALIC><TDUNDERLIN>*</TDUNDERLIN><TDULPOS>0.00</TDULPOS><TDULTHICK>0.00</TDULTHICK><TDULGREY>000</TDULGREY><RED>000</RED><GREEN>000</GREEN><BLUE>000</BLUE><TRANS>000</TRANS><LANGU>E</LANGU><CAPTION>Footer LTIMES 5</CAPTION></item><item><ACTIVE>A</ACTIVE><STYLENAME>Z6MM001S_STYLE_SF</STYLENAME><TDPARGRAPH>S6</TDPARGRAPH><TDPJUSTIFY>BLOCK</TDPJUSTIFY><TDPLDIST>0.60</TDPLDIST><TDPLDISTU>LN</TDPLDISTU><TDPTOP>0.00</TDPTOP><TDPTOPU>CM</TDPTOPU><TDPBOT>0.00</TDPBOT><TDPBOTU>CM</TDPBOTU><TDPLEFT>0.00</TDPLEFT><TDPLEFTU>CM</TDPLEFTU><TDPRIGHT>0.00</TDPRIGHT><TDPRIGHTU>CM</TDPRIGHTU><TDPENTRY>0.00</TDPENTRY><TDPENTRYU>CM</TDPENTRYU><TDNUMLEFT>0.00</TDNUMLEFT><TDNUMOUTL>00</TDNUMOUTL><TDLDEPTH>00</TDLDEPTH><TDLFIRSTIN>0</TDLFIRSTIN><TDLNEXTIND>0</TDLNEXTIND><TDLCOUNT>0</TDLCOUNT><TDFAMILY>TIMES</TDFAMILY><TDHEIGHT>065</TDHEIGHT><TDBOLD>*</TDBOLD><TDITALIC>*</TDITALIC><TDUNDERLIN>*</TDUNDERLIN><TDULPOS>0.00</TDULPOS><TDULTHICK>0.00</TDULTHICK><TDULGREY>000</TDULGREY><RED>000</RED><GREEN>000</GREEN><BLUE>000</BLUE><TRANS>000</TRANS><LANGU>E</LANGU><CAPTION>Footer LTIMES 6</CAPTION></item><item><ACTIVE>A</ACTIVE><STYLENAME>Z6MM001S_STYLE_SF</STYLENAME><TDPARGRAPH>ST</TDPARGRAPH><TDPJUSTIFY>BLOCK</TDPJUSTIFY><TDPLDIST>1.00</TDPLDIST><TDPLDISTU>LN</TDPLDISTU><TDPTOP>0.00</TDPTOP><TDPTOPU>CM</TDPTOPU><TDPBOT>0.00</TDPBOT><TDPBOTU>CM</TDPBOTU><TDPLEFT>0.00</TDPLEFT><TDPLEFTU>CM</TDPLEFTU><TDPRIGHT>0.00</TDPRIGHT><TDPRIGHTU>CM</TDPRIGHTU><TDPENTRY>0.00</TDPENTRY><TDPENTRYU>CM</TDPENTRYU><TDNUMLEFT>0.00</TDNUMLEFT><TDNUMOUTL>00</TDNUMOUTL><TDLDEPTH>00</TDLDEPTH><TDLFIRSTIN>0</TDLFIRSTIN><TDLNEXTIND>0</TDLNEXTIND><TDLCOUNT>0</TDLCOUNT><TDFAMILY>TIMES</TDFAMILY><TDHEIGHT>100</TDHEIGHT><TDBOLD>*</TDBOLD><TDITALIC>*</TDITALIC><TDUNDERLIN>*</TDUNDERLIN><TDULPOS>0.00</TDULPOS><TDULTHICK>0.00</TDULTHICK><TDULGREY>000</TDULGREY><RED>000</RED><GREEN>000</GREEN><BLUE>000</BLUE><TRANS>000</TRANS><LANGU>E</LANGU><CAPTION>Std Paragraph TIMES 10</CAPTION></item></sf:PARAGRAPHS><sf:STRINGS><item><ACTIVE>A</ACTIVE><STYLENAME>Z6MM001S_STYLE_SF</STYLENAME><TDSTRING>C1</TDSTRING><TDSUPER>*</TDSUPER><TDSUB>*</TDSUB><TDSUDIST>0.00</TDSUDIST><TDHIDDEN>*</TDHIDDEN><TDPROTLINE>*</TDPROTLINE><TDHEIGHT>000</TDHEIGHT><TDBOLD>X</TDBOLD><TDITALIC>*</TDITALIC><TDUNDERLIN>*</TDUNDERLIN><TDULPOS>0.00</TDULPOS><TDULTHICK>0.00</TDULTHICK><TDULGREY>000</TDULGREY><RED>000</RED><GREEN>000</GREEN><BLUE>000</BLUE><TRANS>000</TRANS><LANGU>E</LANGU><CAPTION>Bold</CAPTION></item><item><ACTIVE>A</ACTIVE><STYLENAME>Z6MM001S_STYLE_SF</STYLENAME><TDSTRING>C2</TDSTRING><TDSUPER>*</TDSUPER><TDSUB>*</TDSUB><TDSUDIST>0.00</TDSUDIST><TDHIDDEN>*</TDHIDDEN><TDPROTLINE>*</TDPROTLINE><TDHEIGHT>000</TDHEIGHT><TDBOLD>*</TDBOLD><TDITALIC>*</TDITALIC><TDUNDERLIN>X</TDUNDERLIN><TDULPOS>0.00</TDULPOS><TDULTHICK>0.00</TDULTHICK><TDULGREY>000</TDULGREY><RED>000</RED><GREEN>000</GREEN><BLUE>000</BLUE><TRANS>000</TRANS><LANGU>E</LANGU><CAPTION>Under Line</CAPTION></item><item><ACTIVE>A</ACTIVE><STYLENAME>Z6MM001S_STYLE_SF</STYLENAME><TDSTRING>C3</TDSTRING><TDSUPER>*</TDSUPER><TDSUB>*</TDSUB><TDSUDIST>0.00</TDSUDIST><TDHIDDEN>*</TDHIDDEN><TDPROTLINE>*</TDPROTLINE><TDHEIGHT>000</TDHEIGHT><TDBOLD>*</TDBOLD><TDITALIC>X</TDITALIC><TDUNDERLIN>X</TDUNDERLIN><TDULPOS>0.00</TDULPOS><TDULTHICK>0.00</TDULTHICK><TDULGREY>000</TDULGREY><RED>000</RED><GREEN>000</GREEN><BLUE>000</BLUE><TRANS>000</TRANS><LANGU>E</LANGU><CAPTION>Italic</CAPTION></item><item><ACTIVE>A</ACTIVE><STYLENAME>Z6MM001S_STYLE_SF</STYLENAME><TDSTRING>N1</TDSTRING><TDSUPER>*</TDSUPER><TDSUB>*</TDSUB><TDSUDIST>0.00</TDSUDIST><TDHIDDEN>*</TDHIDDEN><TDPROTLINE>*</TDPROTLINE><TDHEIGHT>000</TDHEIGHT><TDBOLD>*</TDBOLD><TDITALIC>*</TDITALIC><TDUNDERLIN>*</TDUNDERLIN><TDULPOS>0.00</TDULPOS><TDULTHICK>0.00</TDULTHICK><TDULGREY>000</TDULGREY><RED>000</RED><GREEN>000</GREEN><BLUE>000</BLUE><TRANS>000</TRANS><LANGU>E</LANGU><CAPTION>Normal</CAPTION></item></sf:STRINGS><sf:TABSTOPS/></sf:SMARTSTYLE>